fastparse/__init__.py
fastparse/base_parser.py
fastparse/utilities.py
fastparser/__init__.py
fastparser/base_parser.py
fastparser/base_site.py
fastparser/utilities.py
tests/__init__.py
tests/test_baseparser.py
tests/test_basesite.py
fastparser-0.2.dist-info/METADATA
fastparser-0.2.dist-info/WHEEL
fastparser-0.2.dist-info/top_level.txt
fastparser-0.2.dist-info/RECORD
